lupa/__init__.py
lupa/lua51.cp38-win32.pyd
lupa/lua52.cp38-win32.pyd
lupa/lua53.cp38-win32.pyd
lupa/lua54.cp38-win32.pyd
lupa/luajit20.cp38-win32.pyd
lupa/luajit21.cp38-win32.pyd
lupa/version.py
lupa-2.6.dist-info/LICENSE.txt
lupa-2.6.dist-info/METADATA
lupa-2.6.dist-info/WHEEL
lupa-2.6.dist-info/top_level.txt
lupa-2.6.dist-info/RECORD
