Metadata-Version: 2.1
Name: lupa
Version: 2.6
Summary: Python wrapper around Lua and LuaJIT
Home-page: https://github.com/scoder/lupa
Author: Stefan Behnel
Author-email: stefan_ml@behnel.de
Maintainer: Lupa-dev mailing list
Maintainer-email: lupa-dev@freelists.org
License: MIT style
Classifier: Development Status :: 5 - Production/Stable
Classifier: Intended Audience :: Developers
Classifier: Intended Audience :: Information Technology
Classifier: Programming Language :: Cython
Classifier: Programming Language :: Python :: 3
Classifier: Programming Language :: Lua
Classifier: Programming Language :: Other Scripting Engines
Classifier: Operating System :: OS Independent
Classifier: Topic :: Software Development
License-File: LICENSE.txt
